tagwriting/__init__.py
tagwriting/main.py
tagwriting-0.3.2.0.dist-info/licenses/LICENSE.md
tagwriting-0.3.2.0.dist-info/METADATA
tagwriting-0.3.2.0.dist-info/WHEEL
tagwriting-0.3.2.0.dist-info/entry_points.txt
tagwriting-0.3.2.0.dist-info/top_level.txt
tagwriting-0.3.2.0.dist-info/RECORD
