Metadata-Version: 2.4
Name: tagwriting
Version: 0.3.2.0
Summary: A CLI tool for tag-based text processing.
Author-email: esehara <esehara@gmail.com>
Project-URL: GitHub, https://github.com/esehara/tagwriting
Classifier: Programming Language :: Python :: 3
Classifier: License :: OSI Approved :: MIT License
Requires-Python: >=3.8
License-File: LICENSE.md
Requires-Dist: click
Requires-Dist: rich
Requires-Dist: readchar
Requires-Dist: watchdog
Requires-Dist: python-dotenv
Requires-Dist: pyyaml
Requires-Dist: requests
Requires-Dist: beautifulsoup4
Dynamic: license-file
